{
	"0": {
		"zoom": [5, 5],
		"name": "Colin",
		"anim": "mc",
		"text": "The food tasted amazing. Thank you so much, Ms. Barbara!",
		
		"next": "1",
	},
	"1": {
		"zoom": [5, 5],
		"name": "Ms. Barbara",
		"anim": "mt",
		"text": "You are always welcome, sweetheart~!",
		
		"next": "2",
	},
	"2": {
		"zoom": [5, 5],
		"name": "Ms. Barbara",
		"anim": "mt",
		"text": "...",
		
		"next": "3",
	},
	"3": {
		"zoom": [5, 5],
		"name": "Ms. Barbara",
		"anim": "mt",
		"text": "Oh, dear...",
		
		"next": "4",
	},
	"4": {
		"zoom": [5, 5],
		"name": "Ms. Barbara",
		"anim": "mt",
		"text": "I hate to ask... but can you help me by bringing your plates to the kitchen sink?",
		
		"next": "5",
	},
	"5": {
		"zoom": [5, 5],
		"name": "Colin",
		"anim": "mc",
		"text": "Oh, uhm—",
		
		"next": "6",
	},
	"6": {
		"zoom": [4, 4],
		"star": "target",
		"name": "Ms. Barbara",
		"anim": "mt",
		"text": "It's just a quick run! Just pick them up and bring them over.",
		
		"next": "7",
	},
	"7": {
		"zoom": [5, 5],
		"star": "player",
		"name": "Ms. Barbara",
		"anim": "mt",
		"text": "We're short on staff today. It will help a lot. Thank you, sweetie! I'll leave you to it.",
		
		"next": "END",
	},
	"END": {
		"node": "/root/GameController",
		"func": "start_next_task",
		"args": [],
		"await": "",
		"hide_box": true,
		
		"comment": "",
	},
}
